vechord-0.2.4.dist-info/METADATA
vechord-0.2.4.dist-info/WHEEL
vechord-0.2.4.dist-info/entry_points.txt
vechord-0.2.4.dist-info/licenses/LICENSE
vechord/__init__.py
vechord/__version__.py
vechord/augment.py
vechord/chunk.py
vechord/cli.py
vechord/client.py
vechord/embedding.py
vechord/errors.py
vechord/evaluate.py
vechord/extract.py
vechord/graph.py
vechord/groundtruth.py
vechord/load.py
vechord/log.py
vechord/model/__init__.py
vechord/model/gemini.py
vechord/model/internal.py
vechord/model/jina.py
vechord/model/llamacloud.py
vechord/model/voyage.py
vechord/model/web.py
vechord/pipeline.py
vechord/provider.py
vechord/py.typed
vechord/registry.py
vechord/rerank.py
vechord/service.py
vechord/spec.py
vechord/typing.py
vechord/utils.py
vechord-0.2.4.dist-info/RECORD
