Metadata-Version: 2.1
Name: vechord
Version: 0.2.4
Summary: VectorChord Python SDK
Classifier: Topic :: Database
Classifier: Intended Audience :: Developers
Classifier: License :: OSI Approved :: Apache Software License
Classifier: Programming Language :: Python :: 3.10
Classifier: Programming Language :: Python :: 3.11
Classifier: Programming Language :: Python :: 3.12
Classifier: Programming Language :: Python :: 3.13
Project-URL: Homepage, https://github.com/tensorchord/vechord
Project-URL: Documentation, https://tensorchord.github.io/vechord/
Project-URL: Repository, https://github.com/tensorchord/vechord.git
Project-URL: Issues, https://github.com/tensorchord/vechord/issues
Requires-Python: >=3.10
Requires-Dist: defspec>=0.4.0
Requires-Dist: falcon>=4.1.0
Requires-Dist: httpx>=0.28.1
Requires-Dist: msgspec>=0.19.0
Requires-Dist: numpy>=2.0.2
Requires-Dist: pgvector>=0.3.6
Requires-Dist: psycopg-pool>=3.2.6
Requires-Dist: psycopg[binary]>=3.2.3
Requires-Dist: pypdfium2==4.30.0
Requires-Dist: pytrec-eval-terrier>=0.5.6
Requires-Dist: rich>=13.9.4
Requires-Dist: typing-extensions~=4.9; python_full_version < "3.11"
Requires-Dist: uuid-utils>=0.10.0
Provides-Extra: openai
Requires-Dist: openai>=1.60.2; extra == "openai"
Provides-Extra: spacy
Requires-Dist: en-core-web-sm; extra == "spacy"
Requires-Dist: spacy>=3.8.4; extra == "spacy"
Provides-Extra: cohere
Requires-Dist: cohere>=5.14.0; extra == "cohere"
Provides-Extra: web
Requires-Dist: uvicorn>=0.34.3; extra == "web"
Requires-Dist: uvloop>=0.21.0; extra == "web"
